jax_fcpe/__init__.py
jax_fcpe/convert.py
jax_fcpe/infer.py
jax_fcpe/model_conformer_naive.py
jax_fcpe/models.py
jax_fcpe/utils.py
jax_fcpe-0.0.6.dist-info/METADATA
jax_fcpe-0.0.6.dist-info/WHEEL
jax_fcpe-0.0.6.dist-info/top_level.txt
jax_fcpe-0.0.6.dist-info/RECORD
